[
  {
    "date": "2026-04-26",
    "title": "2026/4/26 內科醫學會預防醫學暨健康促進研討會(台中場)",
    "publish_date": "2026-03-11",
    "event_id": "7317bd955597",
    "url": "https://www.tsim.org.tw/ehc-tsim/s/w/news_acts/article/7317bd9555974fa39d75e3b3f1a0c9e4",
    "organizer": "台灣內科醫學會",
    "location": "中山醫學大學行政大樓12樓國際會議廳(台中市南區建國北路一段110號)",
    "time_info": "2026年4月26日 (星期日)",
    "registration_method": "直接到現場簽到。",
    "credits_category": "A類",
    "credits": "2",
    "program_info": "發佈時間：115/03/11\n內科醫學會預防醫學暨健康促進研討會(台中場)\n主辦單位：台灣內科醫學會\n地點：中山醫學大學行政大樓12樓國際會議廳(台中市南區建國北路一段110號)\n時間：2026年4月26日 (星期日)\n報到方式：直接到現場簽到。\n學分：內科醫學會 A 類2點\n課程表：\nTime\nTopic\nSpeaker\nModerator\n09:00~09:05\nOpening\n張延亙常務理事\n09:05~09:55\n台灣健康管理產業的發展與機遇\n羅鴻源醫師\n張延亙常務理事\n09:55~10:45\n亞健康的醫學定位與臨床挑戰—從症狀到系統評估\n謝明家醫師\n鄭志賢理事\n10:45~11:00\nPannel Discussion\nALL\n<div",
    "downloads": [
      {
        "text": "預防醫學暨健康促進研討會(台中場)R.pdf",
        "url": "https://www.tsim.org.tw/ehc-tsim/s/viewFile?documentId=f0efab2f79324b8f974f24944836b8d8&fileId="
      }
    ]
  },
  {
    "date": "2026-05-17",
    "title": "2026/5/17 內科醫學會體重管理暨代謝症候群研討會(高雄場)",
    "publish_date": "2026-03-11",
    "event_id": "6c3c853860a6",
    "url": "https://www.tsim.org.tw/ehc-tsim/s/w/news_acts/article/6c3c853860a64d34b0b0d4caeb7ce066",
    "organizer": "台灣內科醫學會",
    "location": "高醫附醫啟川大樓六樓第二講堂(高雄市三民區自由一路100號)",
    "time_info": "2026年5月17日 (星期日)",
    "registration_method": "直接到現場簽到。",
    "credits_category": "A類",
    "credits": "2",
    "program_info": "發佈時間：115/03/11\n內科醫學會體重管理暨代謝症候群研討會(高雄場)\n主辦單位：台灣內科醫學會\n地點：高醫附醫啟川大樓六樓第二講堂(高雄市三民區自由一路100號)\n時間：2026年5月17日 (星期日)\n報到方式：直接到現場簽到。\n學分：內科醫學會 A 類2點\n課程表：\n日期：2026年5月17日（日）\nTime\nTopics\nSpeaker\n10：00– 10：05\nOpening Remark\n劉輝雄院長\n10：05– 10：55\n亞健康的醫學定位與臨床挑戰—從症狀到系統評估\n謝明家院長\n10：55– 11：45\n糖尿病與減重治療的最新發展\n莊立倫醫師\n11：40 – 12：00\nQ&A\n曾競鋒醫師\n<div",
    "downloads": [
      {
        "text": "課程表1150517.pdf",
        "url": "https://www.tsim.org.tw/ehc-tsim/s/viewFile?documentId=db791fd7088a498aa83ba437f0dadcfd&fileId="
      }
    ]
  }
]